{
    "client": [
        {
            "id": "843f3111-a5f2-4968-b02a-bfebe7ec2f44",
            "name": "Realmix",
            "email": "epaynton0@prlog.org",
            "phoneNumber": "573-809-2737",
            "code": "56-123",
            "addressFact": "Apt 1972",
            "syncId": "f75aeacb-8a8a-42a6-a070-b95ff9a7a968",
            "active": true
        },
        {
            "id": "65162e36-1f00-49d9-a28f-cde3d236e8d0",
            "name": "Eidel",
            "email": "ogriniov1@opera.com",
            "phoneNumber": "558-245-5956",
            "code": "56-122",
            "addressFact": "Suite 3",
            "syncId": "7ee84e29-b9d0-48b1-9295-20f5c90944ac",
            "active": true
        },
        {
            "id": "5868ca59-fc82-4518-b681-aa2a9872351f",
            "name": "Agivu",
            "email": "alightbody2@ameblo.jp",
            "phoneNumber": "796-386-0562",
            "code": "28930-000",
            "addressFact": "Apt 359",
            "syncId": "3f6708e3-da89-4b09-80a9-a326a16bf851",
            "active": false
        },
        {
            "id": "aa709a17-f016-490f-bb1b-4d760a8fdd9e",
            "name": "Flashdog",
            "email": "ptrass3@cornell.edu",
            "phoneNumber": "551-253-8486",
            "code": "56-124",
            "addressFact": "Room 1925",
            "syncId": "be384bda-6def-467e-955a-fc673d9307d7",
            "active": true
        },
        {
            "id": "14671477-7401-4ea4-8604-dfeb925903be",
            "name": "Dazzlesphere",
            "email": "mcrossley4@slate.com",
            "phoneNumber": "545-394-5661",
            "code": "5914",
            "addressFact": "PO Box 48862",
            "syncId": "5cfaf405-31ea-4a15-bce4-0e9607bfdec4",
            "active": false
        },
        {
            "id": "ed3755ca-eddc-4973-bf6b-e4b749123a33",
            "name": "Rhycero",
            "email": "bcasotti5@comcast.net",
            "phoneNumber": "921-830-1519",
            "code": "56-125",
            "addressFact": "Room 108",
            "syncId": "f5ee0b5c-4d35-40fd-ac06-e992eb0c5b41",
            "active": false
        },
        {
            "id": "8c7c013a-88b1-4e73-b195-77312c3b15ce",
            "name": "Devpulse",
            "email": "anaish6@xrea.com",
            "phoneNumber": "373-525-6779",
            "code": "1950",
            "addressFact": "Room 1877",
            "syncId": "62652d47-5e62-4127-b932-3fea5ee2cb73",
            "active": true
        },
        {
            "id": "0800106a-02d2-46b5-9a21-c29beab023cd",
            "name": "Cogidoo",
            "email": "lfinnie7@springer.com",
            "phoneNumber": "106-413-1866",
            "code": "56-126",
            "addressFact": "Suite 9",
            "syncId": "3c5ab872-7330-41bc-a70f-24c16e6f4b65",
            "active": true
        },
        {
            "id": "232217f3-b031-46fa-bd19-f52f7accddaf",
            "name": "Twitterworks",
            "email": "sspratley8@intel.com",
            "phoneNumber": "202-462-8125",
            "code": "00928",
            "addressFact": "2nd Floor",
            "syncId": "e34d86cb-7530-4d5d-865d-2150407298f1",
            "active": false
        },
        {
            "id": "8d9fada1-78ae-41ca-9af3-4530d19b9ac1",
            "name": "Centidel",
            "email": "hreddlesden9@auda.org.au",
            "phoneNumber": "529-933-7381",
            "code": "63001",
            "addressFact": "Room 848",
            "syncId": "43958a48-9022-40f0-aefe-2e214dc773b2",
            "active": true
        },
        {
            "id": "1cc72f5f-083d-4d76-8f8b-e84f18209015",
            "name": "Zoovu",
            "email": "vmargueritea@nature.com",
            "phoneNumber": "539-977-9566",
            "code": "11111111",
            "addressFact": "PO Box 61787",
            "syncId": "9e3975d0-3220-4e38-b935-605e8bd4d97a",
            "active": false
        },
        {
            "id": "52e1ce01-6826-479e-95c4-4703e471fdc4",
            "name": "Jabbertype",
            "email": "ekitchenerb@cpanel.net",
            "phoneNumber": "566-831-5894",
            "code": "5200",
            "addressFact": "Room 373",
            "syncId": "9304197c-e38c-461b-bff5-f3a7c8a106bc",
            "active": false
        },
        {
            "id": "6a641721-223c-481b-b97f-40e4cae566b0",
            "name": "Tagpad",
            "email": "rmccuec@time.com",
            "phoneNumber": "367-465-3335",
            "code": "397325",
            "addressFact": "13th Floor",
            "syncId": "48c5ea1f-9e83-4f83-9a97-595f47c06a30",
            "active": true
        },
        {
            "id": "f4fde496-df88-40c6-99b4-00159ab28626",
            "name": "Voomm",
            "email": "asacksd@washington.edu",
            "phoneNumber": "645-624-7301",
            "code": "2560-057",
            "addressFact": "20th Floor",
            "syncId": "784de27e-b896-42a5-bb6d-9120f2aeb5ac",
            "active": false
        },
        {
            "id": "36ef47fb-8abd-44fe-867b-64fc30da40fc",
            "name": "Divavu",
            "email": "cbourtoumieuxe@godaddy.com",
            "phoneNumber": "322-576-6925",
            "code": "5105",
            "addressFact": "4th Floor",
            "syncId": "4f44f69a-04b9-4e9d-a707-e2d67fc1e6f9",
            "active": false
        },
        {
            "id": "79beb5ad-30a0-4990-9dc3-818dce079991",
            "name": "Zoomdog",
            "email": "bmartinotf@rakuten.co.jp",
            "phoneNumber": "743-655-8706",
            "code": "1658",
            "addressFact": "18th Floor",
            "syncId": "e7030135-aaa0-4e5d-b665-a3a6a3544906",
            "active": true
        },
        {
            "id": "7e164386-8ce4-42e1-b1d3-bce733165ba8",
            "name": "Fivebridge",
            "email": "gtomczykowskig@answers.com",
            "phoneNumber": "738-742-6268",
            "code": "11111111",
            "addressFact": "PO Box 28482",
            "syncId": "e044fb0c-421a-42a0-b3e9-1549aa26d166",
            "active": true
        },
        {
            "id": "53f4b7c7-bfa6-482b-b15a-8f9b94f08b4c",
            "name": "Snaptags",
            "email": "hgrayerh@illinois.edu",
            "phoneNumber": "816-564-5589",
            "code": "11111111",
            "addressFact": "Apt 1076",
            "syncId": "b202865a-8d17-4ab9-8956-00f4acc0723a",
            "active": false
        },
        {
            "id": "c7b29740-7d74-4953-b715-e69c79b3b9af",
            "name": "Divanoodle",
            "email": "dkilfetheri@answers.com",
            "phoneNumber": "705-911-5068",
            "code": "11111111",
            "addressFact": "Room 1547",
            "syncId": "917f5e3e-7577-4934-a941-452f5b2bf003",
            "active": true
        },
        {
            "id": "fa913ac0-daa1-4ab0-bd69-91e157f4d2e0",
            "name": "Mydeo",
            "email": "lhumblej@sitemeter.com",
            "phoneNumber": "886-240-7761",
            "code": "363303",
            "addressFact": "Apt 631",
            "syncId": "47b1c55e-95de-470a-9490-741534fc8f02",
            "active": false
        },
        {
            "id": "bc61cc2f-8084-48d9-834f-427ae950caf8",
            "name": "Vipe",
            "email": "malflattk@dagondesign.com",
            "phoneNumber": "822-527-5124",
            "code": "03009",
            "addressFact": "Room 815",
            "syncId": "373cf60b-dded-434c-a0fb-a864b7e6f6d5",
            "active": true
        },
        {
            "id": "56912064-ade5-457b-9c9b-dfb7af8618e7",
            "name": "Plajo",
            "email": "fgotfreyl@va.gov",
            "phoneNumber": "770-626-5501",
            "code": "11111111",
            "addressFact": "14th Floor",
            "syncId": "c154fa9f-cd21-426c-95d7-2fef1cd79358",
            "active": true
        },
        {
            "id": "296f55e8-67b7-4410-8fef-c7fa8cfe9558",
            "name": "Ainyx",
            "email": "ssimoninim@shop-pro.jp",
            "phoneNumber": "413-939-3116",
            "code": "01129",
            "addressFact": "Suite 3",
            "syncId": "be831294-bf35-482e-96ae-7a63a26573e6",
            "active": true
        },
        {
            "id": "38a85430-f0bb-4afb-8fe9-1a7e20b060e6",
            "name": "Teklist",
            "email": "mgeydonn@omniture.com",
            "phoneNumber": "251-364-0047",
            "code": "11111111",
            "addressFact": "2nd Floor",
            "syncId": "d3e389fb-1911-4e65-81e4-46871525a651",
            "active": true
        },
        {
            "id": "629c490c-3cf7-411a-b376-6a6702730443",
            "name": "Quinu",
            "email": "kthundercliffeo@army.mil",
            "phoneNumber": "347-559-2011",
            "code": "P56",
            "addressFact": "Apt 1899",
            "syncId": "f93010ad-f149-489f-b966-6e941ab8255d",
            "active": true
        },
        {
            "id": "e406d154-89bc-48d6-9307-17eda4d2fc0c",
            "name": "Skalith",
            "email": "aoppyp@chronoengine.com",
            "phoneNumber": "624-546-6412",
            "code": "143912",
            "addressFact": "7th Floor",
            "syncId": "7719dbda-d580-4745-806d-e10e9a5a8b50",
            "active": true
        },
        {
            "id": "53fed5b4-bc85-4941-9cb4-2d05d6b26cc0",
            "name": "Devpulse",
            "email": "tdorningq@myspace.com",
            "phoneNumber": "280-572-8844",
            "code": "11111111",
            "addressFact": "PO Box 2885",
            "syncId": "da199a83-a8fc-4389-b4c5-ad1f1edd3146",
            "active": true
        },
        {
            "id": "6e823278-0dad-4301-ab32-ff8fadbd4177",
            "name": "Browsebug",
            "email": "clanpherer@google.ca",
            "phoneNumber": "636-598-9612",
            "code": "541 70",
            "addressFact": "Suite 100",
            "syncId": "f81cb229-edc9-4451-8a90-b8eba1be161f",
            "active": true
        },
        {
            "id": "5bdc94ba-7d34-49ca-a037-3abbdb0eb683",
            "name": "Riffpath",
            "email": "dtabrams@so-net.ne.jp",
            "phoneNumber": "751-754-4372",
            "code": "11111111",
            "addressFact": "Room 1753",
            "syncId": "0ed9e796-bce1-4f30-88c1-def08f9d2425",
            "active": false
        },
        {
            "id": "2c7ca9a6-1b12-4c8a-819a-1d59f285a301",
            "name": "Jabbersphere",
            "email": "bkillet@typepad.com",
            "phoneNumber": "335-386-1685",
            "code": "11111111",
            "addressFact": "PO Box 32613",
            "syncId": "c7af218b-9f49-45ac-bbb6-4cbf01de6dae",
            "active": false
        },
        {
            "id": "afd4fdf7-fc90-4dcf-b442-aa30235aaf73",
            "name": "Myworks",
            "email": "ncoggingsu@businessinsider.com",
            "phoneNumber": "951-490-9577",
            "code": "11111111",
            "addressFact": "PO Box 28444",
            "syncId": "23c18b56-998d-40bc-99a8-e0e299620e26",
            "active": true
        },
        {
            "id": "b9225ee4-be83-4804-b78f-596b39915deb",
            "name": "Feedspan",
            "email": "bolssonv@macromedia.com",
            "phoneNumber": "265-606-9441",
            "code": "11111111",
            "addressFact": "9th Floor",
            "syncId": "a1a91880-bd98-4263-bc9a-666ad2515fc7",
            "active": false
        },
        {
            "id": "76d6617f-8bca-4d55-8c57-0ff636a00abc",
            "name": "Devpulse",
            "email": "tmanoelliw@alexa.com",
            "phoneNumber": "296-887-7345",
            "code": "452122",
            "addressFact": "Suite 91",
            "syncId": "2685eb0e-ff74-4fd0-8b48-9f802aae8efb",
            "active": true
        },
        {
            "id": "ee56ce26-48ad-41e3-84a0-40b8e1e144b9",
            "name": "Browsebug",
            "email": "bfidellix@smugmug.com",
            "phoneNumber": "212-911-0872",
            "code": "11111111",
            "addressFact": "Apt 1609",
            "syncId": "f9f2b923-85fd-4ffa-a7e2-01eaea3925b7",
            "active": true
        },
        {
            "id": "81ee2017-c96a-4ba2-9554-437ceee73435",
            "name": "Zoonoodle",
            "email": "wnanniniy@clickbank.net",
            "phoneNumber": "177-268-6047",
            "code": "11111111",
            "addressFact": "Apt 787",
            "syncId": "a5ad56d0-c4e2-4c84-956b-367aa16f5ff3",
            "active": true
        },
        {
            "id": "421045e8-5ef3-4d86-81ec-68cb1687bcd7",
            "name": "Twitternation",
            "email": "pkrahlz@imgur.com",
            "phoneNumber": "695-683-2438",
            "code": "747 20",
            "addressFact": "Room 1308",
            "syncId": "808bc491-2aed-4731-badf-52df3e63c73b",
            "active": true
        },
        {
            "id": "ef447c53-4f43-4c79-ad3b-f45fef89241f",
            "name": "Skaboo",
            "email": "kmart10@ucla.edu",
            "phoneNumber": "917-832-8009",
            "code": "5875",
            "addressFact": "PO Box 36427",
            "syncId": "55f3180c-0367-41c2-89b8-d0c52d89eafa",
            "active": true
        },
        {
            "id": "311f0d26-b697-4049-97d2-ed976c90daca",
            "name": "Linkbridge",
            "email": "jnorfolk11@un.org",
            "phoneNumber": "816-636-2240",
            "code": "11111111",
            "addressFact": "PO Box 86682",
            "syncId": "613c506b-16bc-4efe-9b65-6cf919dc2d98",
            "active": true
        },
        {
            "id": "fbd29c23-c30b-41c5-94a0-59db32491828",
            "name": "Zoomlounge",
            "email": "varmour12@biglobe.ne.jp",
            "phoneNumber": "899-871-6082",
            "code": "11111111",
            "addressFact": "Apt 928",
            "syncId": "6d37192a-d59c-48bb-b2a7-4c36801bb08f",
            "active": false
        },
        {
            "id": "d23aafe7-d98c-434d-8596-ab49feedf118",
            "name": "Kwimbee",
            "email": "dgadault13@google.pl",
            "phoneNumber": "102-212-2084",
            "code": "859-0413",
            "addressFact": "Suite 64",
            "syncId": "60b7cd40-9244-429b-b787-00e1d91ca014",
            "active": true
        },
        {
            "id": "5c9a325e-a8b1-4a62-94fc-573255b5c271",
            "name": "Dabjam",
            "email": "bdowsing14@npr.org",
            "phoneNumber": "778-231-4287",
            "code": "421-0522",
            "addressFact": "PO Box 19565",
            "syncId": "51020e2e-00c4-4a40-a3d6-12edc3eea80e",
            "active": true
        },
        {
            "id": "aa60dcae-c17a-4c95-b91b-76b0c7ccdc88",
            "name": "Jaxnation",
            "email": "ctrethowan15@google.com.au",
            "phoneNumber": "672-435-0316",
            "code": "11111111",
            "addressFact": "Apt 207",
            "syncId": "e1404453-2d69-4d4d-9694-6ea73242b262",
            "active": false
        },
        {
            "id": "e95f3e9c-38ce-4159-b9c9-ae7ed1000539",
            "name": "Zoomzone",
            "email": "mperrin16@whitehouse.gov",
            "phoneNumber": "187-323-7108",
            "code": "11111111",
            "addressFact": "1st Floor",
            "syncId": "2463ac23-7627-47a2-9bfb-5438e311ac46",
            "active": true
        },
        {
            "id": "9ad51d73-ecc6-4276-920a-a979763f3a35",
            "name": "Kwilith",
            "email": "agrouse17@ucla.edu",
            "phoneNumber": "255-784-1702",
            "code": "11111111",
            "addressFact": "3rd Floor",
            "syncId": "b7de7884-a897-403c-8fb7-e71c797f2a84",
            "active": true
        },
        {
            "id": "b29e07e6-a1da-472a-b414-13763a8d0f35",
            "name": "Cogilith",
            "email": "bcrehan18@over-blog.com",
            "phoneNumber": "532-806-9004",
            "code": "6022",
            "addressFact": "6th Floor",
            "syncId": "b47afc30-87e3-43d6-939c-7c7912699ac9",
            "active": false
        },
        {
            "id": "4441bdec-4fb2-4d4d-a339-0fd6a6e0c3d1",
            "name": "Photobean",
            "email": "kantonoyev19@ehow.com",
            "phoneNumber": "208-522-3253",
            "code": "83727",
            "addressFact": "Suite 88",
            "syncId": "02570f02-0735-4a22-8c2a-e4ea9604e175",
            "active": false
        },
        {
            "id": "0a321d6a-de53-4da3-a85d-8e7a86b22f14",
            "name": "Wikivu",
            "email": "sstile1a@princeton.edu",
            "phoneNumber": "400-174-5995",
            "code": "11111111",
            "addressFact": "Suite 98",
            "syncId": "61523e49-8705-4def-a582-7e4625679b54",
            "active": true
        },
        {
            "id": "6b418125-fd8f-4191-85a1-c56a53d38a5d",
            "name": "Eare",
            "email": "sbon1b@printfriendly.com",
            "phoneNumber": "951-558-4549",
            "code": "11111111",
            "addressFact": "Room 1401",
            "syncId": "cae0ea4b-c0d6-4c9f-b243-19ab82bdea78",
            "active": false
        },
        {
            "id": "113a486b-1908-43b6-ad01-778ccd285a20",
            "name": "Edgeclub",
            "email": "ftredwell1c@nymag.com",
            "phoneNumber": "122-607-0354",
            "code": "5504",
            "addressFact": "Room 1345",
            "syncId": "18464ec4-6f53-4562-8063-d79e4b734fdd",
            "active": true
        },
        {
            "id": "bf122e97-e8b5-4c81-84c9-82236ab4cee0",
            "name": "Skilith",
            "email": "cdreigher1d@wikispaces.com",
            "phoneNumber": "665-479-2089",
            "code": "11111111",
            "addressFact": "Room 1364",
            "syncId": "8561a934-4f1d-4e51-a0a5-0c6b5e4190e6",
            "active": true
        },
        {
            "id": "fc49dd96-b67c-4a80-8948-50a6094fbc50",
            "name": "Blogtags",
            "email": "cflacke1e@ed.gov",
            "phoneNumber": "449-337-9805",
            "code": "11111111",
            "addressFact": "Suite 96",
            "syncId": "76b8e334-291f-4d40-99e0-3ad940090851",
            "active": true
        },
        {
            "id": "62a8bc92-69d9-4587-812b-ed4263465c20",
            "name": "Roombo",
            "email": "phuckster1f@4shared.com",
            "phoneNumber": "228-859-3861",
            "code": "357937",
            "addressFact": "PO Box 89566",
            "syncId": "67ad2ef2-adb8-4d3c-aa36-ee267377f158",
            "active": false
        },
        {
            "id": "d0dee71c-e6a9-4303-9d6c-333bdccb01af",
            "name": "Divape",
            "email": "ischukraft1g@netlog.com",
            "phoneNumber": "502-765-1836",
            "code": "11111111",
            "addressFact": "Room 1714",
            "syncId": "ea8bd2bf-c30d-4c35-a630-7aef0d2085ab",
            "active": true
        },
        {
            "id": "0554d922-fc5d-49ec-9283-2da02e290a60",
            "name": "Centizu",
            "email": "ededantesie1h@sbwire.com",
            "phoneNumber": "821-700-6310",
            "code": "11111111",
            "addressFact": "8th Floor",
            "syncId": "d68b430c-db7c-4ab1-86ce-62e499cfb4f0",
            "active": true
        },
        {
            "id": "24e43351-df72-48cd-b048-feaf1a2ec924",
            "name": "Devbug",
            "email": "escott1i@yahoo.co.jp",
            "phoneNumber": "349-199-2432",
            "code": "3060-323",
            "addressFact": "Room 183",
            "syncId": "1f3ff347-be47-4896-9e42-cc65cedd9528",
            "active": false
        },
        {
            "id": "fdbec7ee-5049-4407-a57e-8ac37487cbef",
            "name": "Divape",
            "email": "cromaines1j@nytimes.com",
            "phoneNumber": "992-351-7085",
            "code": "33190",
            "addressFact": "Apt 380",
            "syncId": "ca3a7635-d449-4db4-9a07-a38a83b67866",
            "active": true
        },
        {
            "id": "ab4b909b-5d54-4a10-83ef-b0105c4dac40",
            "name": "Photobug",
            "email": "pbiasetti1k@xing.com",
            "phoneNumber": "497-137-4016",
            "code": "11111111",
            "addressFact": "PO Box 39273",
            "syncId": "0b59a7ee-2ee6-460c-ac8e-816750a2c817",
            "active": false
        },
        {
            "id": "0dc09280-88ef-42aa-a171-eb66175e8cb5",
            "name": "Quimm",
            "email": "wsimnor1l@ucla.edu",
            "phoneNumber": "595-558-9847",
            "code": "3244",
            "addressFact": "Suite 63",
            "syncId": "d3623dce-685c-4a8e-9314-b044bb6562ab",
            "active": false
        },
        {
            "id": "3512547d-0993-4dce-b44a-016b4903673f",
            "name": "Devpulse",
            "email": "msalsbury1m@jalbum.net",
            "phoneNumber": "796-466-7899",
            "code": "22840",
            "addressFact": "Apt 1795",
            "syncId": "95116d0a-99da-4b8f-9474-9f89b3f33dc1",
            "active": true
        },
        {
            "id": "2447a55f-96da-4611-bf5e-fdc66140516b",
            "name": "Quinu",
            "email": "dgleeson1n@sitemeter.com",
            "phoneNumber": "231-144-5210",
            "code": "44-352",
            "addressFact": "Apt 1768",
            "syncId": "4355531d-4ed5-46df-9fd1-baaeb21bc3da",
            "active": false
        },
        {
            "id": "def6632f-7d83-4d2a-b886-125913ffd53d",
            "name": "Edgewire",
            "email": "btyrwhitt1o@addthis.com",
            "phoneNumber": "281-305-2995",
            "code": "11111111",
            "addressFact": "PO Box 33836",
            "syncId": "f4a69af8-4f7b-439e-84cb-83aaf1ad3e67",
            "active": false
        },
        {
            "id": "1e7334f2-d53e-4430-b66b-098f3b3b63c9",
            "name": "Twimbo",
            "email": "apriscott1p@sciencedirect.com",
            "phoneNumber": "351-777-6227",
            "code": "11111111",
            "addressFact": "20th Floor",
            "syncId": "158a0082-9fc8-445e-9113-8ffbf0e65afb",
            "active": false
        },
        {
            "id": "daa30519-42b7-437e-bcd8-873724e52777",
            "name": "Devpoint",
            "email": "lvarley1q@tiny.cc",
            "phoneNumber": "611-909-1708",
            "code": "739 44",
            "addressFact": "5th Floor",
            "syncId": "90ace4ff-d2d6-4460-89bd-9585780f76a9",
            "active": true
        },
        {
            "id": "1997677e-4788-43ef-ab25-410d34fc8be7",
            "name": "Photobug",
            "email": "gblaydon1r@pagesperso-orange.fr",
            "phoneNumber": "194-904-5106",
            "code": "11111111",
            "addressFact": "Apt 693",
            "syncId": "d03b82a9-4480-4744-9ff3-fde874c191b4",
            "active": true
        },
        {
            "id": "2749f1a8-6188-4fb8-b82f-5648a6f230bb",
            "name": "Edgeclub",
            "email": "fballoch1s@about.com",
            "phoneNumber": "757-231-0446",
            "code": "11111111",
            "addressFact": "16th Floor",
            "syncId": "1f86bef7-b719-4f28-ac1d-352394d465f0",
            "active": false
        },
        {
            "id": "0bcf6880-39f0-4629-ad81-a00471e8b7ae",
            "name": "Skimia",
            "email": "mdarwent1t@dagondesign.com",
            "phoneNumber": "142-282-3381",
            "code": "32-854",
            "addressFact": "Room 1815",
            "syncId": "36238cac-84b7-4810-8cce-6c5561bcd546",
            "active": true
        },
        {
            "id": "65d98561-bc43-44b1-b866-b6d83805de6b",
            "name": "Izio",
            "email": "jgueinn1u@zimbio.com",
            "phoneNumber": "919-992-9729",
            "code": "2213",
            "addressFact": "Room 1955",
            "syncId": "32c9091e-b566-4d15-82d7-b64ab43e29a1",
            "active": false
        },
        {
            "id": "790bab23-51ad-4f42-ba2c-f07248720790",
            "name": "InnoZ",
            "email": "kmorit1v@berkeley.edu",
            "phoneNumber": "312-472-3326",
            "code": "11111111",
            "addressFact": "PO Box 17347",
            "syncId": "7ea2c45c-3649-40ff-bd4f-8cc8d58fde77",
            "active": false
        },
        {
            "id": "dc82037a-95e6-44ad-919f-5d5744104631",
            "name": "Mynte",
            "email": "ziacabucci1w@latimes.com",
            "phoneNumber": "644-211-3271",
            "code": "11111111",
            "addressFact": "Apt 100",
            "syncId": "2703f3a6-8981-4278-b5b2-a52102d6a618",
            "active": true
        },
        {
            "id": "b829dc5f-f1eb-4155-b995-f171fab6c033",
            "name": "Gabspot",
            "email": "cteesdale1x@telegraph.co.uk",
            "phoneNumber": "825-686-9022",
            "code": "11111111",
            "addressFact": "PO Box 98476",
            "syncId": "c799a153-4c0e-43c4-a203-c40e618da71f",
            "active": false
        },
        {
            "id": "a0aaa9fd-8067-4b3f-908d-3b0a535a0c90",
            "name": "Cogilith",
            "email": "kilyukhov1y@hhs.gov",
            "phoneNumber": "425-530-0016",
            "code": "11111111",
            "addressFact": "Suite 24",
            "syncId": "7a1c65e0-7335-48e2-bc06-a2e1a110b49e",
            "active": false
        },
        {
            "id": "0a359d7f-c465-4cbc-86e9-d6ff123eedd3",
            "name": "Roomm",
            "email": "bmehaffey1z@patch.com",
            "phoneNumber": "577-717-5122",
            "code": "1808",
            "addressFact": "PO Box 47020",
            "syncId": "a8239b5b-fe47-477a-b5a8-a9c129d3d84e",
            "active": false
        },
        {
            "id": "75cb3466-0e67-4adb-a2f3-c463ea9b860c",
            "name": "Devbug",
            "email": "tcadwaladr20@fastcompany.com",
            "phoneNumber": "624-603-7291",
            "code": "11111111",
            "addressFact": "Room 1896",
            "syncId": "907a178e-3c50-4c3f-9276-579b0a0a79f9",
            "active": true
        },
        {
            "id": "5138afdd-0b85-4755-9062-65960da079dc",
            "name": "Tambee",
            "email": "bjaggs21@slideshare.net",
            "phoneNumber": "639-994-1858",
            "code": "87041 CEDEX 1",
            "addressFact": "Apt 578",
            "syncId": "eb7b03d3-277d-4cb4-9ce3-0f5ed9a53368",
            "active": false
        },
        {
            "id": "02a966d5-a794-43db-8b1a-7c6c9ec2cf71",
            "name": "Topdrive",
            "email": "dbrowne22@webnode.com",
            "phoneNumber": "800-729-9502",
            "code": "11111111",
            "addressFact": "7th Floor",
            "syncId": "80974f49-f231-44ff-b478-fd2f562c68d6",
            "active": false
        },
        {
            "id": "4e39d708-94a3-465a-8a9f-b552acf0e07d",
            "name": "Topdrive",
            "email": "scullinane23@hubpages.com",
            "phoneNumber": "122-500-3258",
            "code": "11111111",
            "addressFact": "3rd Floor",
            "syncId": "9f929832-6081-49db-94d6-7e5d398ebad2",
            "active": false
        },
        {
            "id": "d2d03556-241a-4608-bf3a-d2dc3ffde5e1",
            "name": "Photobug",
            "email": "fgarritley24@parallels.com",
            "phoneNumber": "483-992-1703",
            "code": "82001",
            "addressFact": "PO Box 21359",
            "syncId": "d6bf9c07-0bd3-47ed-b9ac-288e17bd86ac",
            "active": true
        },
        {
            "id": "4061e0f1-bd89-4363-b836-5b17853d2ebf",
            "name": "Dabtype",
            "email": "gmerlin25@technorati.com",
            "phoneNumber": "129-436-0631",
            "code": "11111111",
            "addressFact": "12th Floor",
            "syncId": "380e29cc-44d8-45eb-9c17-4099f513803c",
            "active": false
        },
        {
            "id": "bca9c422-5d78-4eae-adc9-99a818d7d920",
            "name": "Tagfeed",
            "email": "lyaneev26@amazon.co.jp",
            "phoneNumber": "322-414-1887",
            "code": "11111111",
            "addressFact": "PO Box 54030",
            "syncId": "583c844e-537c-4d27-b220-288c546787ce",
            "active": false
        },
        {
            "id": "b9849c8c-3066-400b-9998-4339917d2f2e",
            "name": "Oyonder",
            "email": "cbreckell27@spotify.com",
            "phoneNumber": "372-804-3674",
            "code": "4510-469",
            "addressFact": "Room 1008",
            "syncId": "79943a23-ebc5-4956-a939-9bb3ec212a9e",
            "active": true
        },
        {
            "id": "94c6bd12-d7a4-4c4c-b6c5-c7157ccb4fa7",
            "name": "Mydeo",
            "email": "bgannan28@psu.edu",
            "phoneNumber": "961-196-1458",
            "code": "11111111",
            "addressFact": "12th Floor",
            "syncId": "d03c485c-3ae5-4329-8e3f-81b2a036900f",
            "active": true
        },
        {
            "id": "45a7d26e-99a5-4d7e-98b6-6ea865ed2af3",
            "name": "Brainsphere",
            "email": "lbibbie29@washington.edu",
            "phoneNumber": "224-714-9420",
            "code": "250618",
            "addressFact": "PO Box 9600",
            "syncId": "ee4fcf28-2458-45ca-bcd8-d4f28a33487e",
            "active": false
        },
        {
            "id": "1af5bd9c-2426-436a-ac46-bc05221c14e6",
            "name": "Zoomlounge",
            "email": "pwetwood2a@about.com",
            "phoneNumber": "605-264-0123",
            "code": "683 01",
            "addressFact": "Room 78",
            "syncId": "5b20b1fd-0f80-4e47-9a8d-16dc5a26da6d",
            "active": false
        },
        {
            "id": "8264010b-1f41-4425-b28e-5b8214ccd05d",
            "name": "Skipstorm",
            "email": "vbear2b@smh.com.au",
            "phoneNumber": "652-232-5497",
            "code": "617820",
            "addressFact": "Room 1528",
            "syncId": "e608ee29-a67e-4278-be04-0cca855b3423",
            "active": true
        },
        {
            "id": "62a290ae-2135-4417-933d-b47dcd2b48b2",
            "name": "Shuffledrive",
            "email": "oleport2c@dot.gov",
            "phoneNumber": "984-549-2742",
            "code": "11111111",
            "addressFact": "Room 494",
            "syncId": "e29da85f-b0d0-4efb-8efd-c7968b4f0456",
            "active": true
        },
        {
            "id": "7d7f7b90-62d0-4bd5-9f49-9bd09a48848f",
            "name": "Reallinks",
            "email": "rcrotty2d@wunderground.com",
            "phoneNumber": "156-930-7593",
            "code": "11111111",
            "addressFact": "Suite 65",
            "syncId": "99a3f126-76ce-4992-bb2f-d450a20990f9",
            "active": true
        },
        {
            "id": "104c1191-7f7a-41fc-8c8e-561846668120",
            "name": "Oozz",
            "email": "rjordon2e@engadget.com",
            "phoneNumber": "688-741-7601",
            "code": "10030",
            "addressFact": "Apt 1512",
            "syncId": "bb464a4f-3037-4f3f-8ce0-735af70660ad",
            "active": false
        },
        {
            "id": "8ddbb24e-c72a-4121-913d-a0e08983c58a",
            "name": "Meedoo",
            "email": "balexander2f@tiny.cc",
            "phoneNumber": "476-440-1312",
            "code": "89-340",
            "addressFact": "Suite 53",
            "syncId": "85493159-b64f-408f-87af-022c983a4837",
            "active": false
        },
        {
            "id": "f4810abe-b5ff-40f9-a6d8-e45a8dfbdbc2",
            "name": "Voolith",
            "email": "trodd2g@flavors.me",
            "phoneNumber": "234-693-2649",
            "code": "11111111",
            "addressFact": "1st Floor",
            "syncId": "9be3597f-1796-4e6a-8980-4ca1af22f6ed",
            "active": false
        },
        {
            "id": "c7a10101-766b-48d3-9dc3-1bce4e996821",
            "name": "Devpoint",
            "email": "asaphir2h@army.mil",
            "phoneNumber": "594-552-5814",
            "code": "702 31",
            "addressFact": "Apt 615",
            "syncId": "3c3b38a3-a177-4189-89fe-962043089786",
            "active": false
        },
        {
            "id": "14efa27d-6510-4903-b2da-43de1ff62932",
            "name": "Dynava",
            "email": "rmarcam2i@ask.com",
            "phoneNumber": "866-616-9004",
            "code": "11111111",
            "addressFact": "14th Floor",
            "syncId": "bc34f6dd-0139-455e-acab-b33bb7f90e27",
            "active": false
        },
        {
            "id": "903fd4f0-d9ee-4227-9de6-544dd673ce68",
            "name": "Jaxworks",
            "email": "dfinker2j@miitbeian.gov.cn",
            "phoneNumber": "268-441-6489",
            "code": "11111111",
            "addressFact": "PO Box 38886",
            "syncId": "19481944-61e9-46a9-a580-ca63ee183cf1",
            "active": true
        },
        {
            "id": "1285d965-0a2e-4db2-a261-696729117e96",
            "name": "Topicblab",
            "email": "mlivezley2k@booking.com",
            "phoneNumber": "318-563-8510",
            "code": "12103",
            "addressFact": "PO Box 56205",
            "syncId": "69b6e3e2-5aec-47bc-ad28-4a3283ae1de7",
            "active": true
        },
        {
            "id": "c392e847-f806-4e7c-b758-e1411607b23e",
            "name": "Devpoint",
            "email": "pbirchill2l@nyu.edu",
            "phoneNumber": "305-333-4492",
            "code": "4290",
            "addressFact": "Suite 31",
            "syncId": "9bf157f0-e56e-4d49-9985-12290450fd74",
            "active": true
        },
        {
            "id": "09f1e3e4-3c57-41aa-8eae-688aa51c7dd5",
            "name": "Skippad",
            "email": "eokelleher2m@reuters.com",
            "phoneNumber": "159-878-1419",
            "code": "11111111",
            "addressFact": "15th Floor",
            "syncId": "a4eb9f84-84f3-40ad-8be8-27cef93c13a1",
            "active": false
        },
        {
            "id": "2d8067f1-26d2-4773-b3d9-3a5837246ccc",
            "name": "Voomm",
            "email": "gcopson2n@springer.com",
            "phoneNumber": "302-898-5644",
            "code": "11111111",
            "addressFact": "PO Box 5842",
            "syncId": "852aa109-aeb9-438f-9728-be3406ab1779",
            "active": false
        },
        {
            "id": "063cec75-d02d-4793-896f-590b01dc2235",
            "name": "Roodel",
            "email": "dkembery2o@is.gd",
            "phoneNumber": "699-664-4214",
            "code": "169336",
            "addressFact": "PO Box 53173",
            "syncId": "684927cb-7679-4a29-a683-c8fc426863a5",
            "active": false
        },
        {
            "id": "71f37dfa-f3f5-4823-a0e7-00ed982eee6b",
            "name": "Innojam",
            "email": "cscrease2p@woothemes.com",
            "phoneNumber": "943-469-5061",
            "code": "42-256",
            "addressFact": "Suite 54",
            "syncId": "2a6d2e91-73fa-40c3-aec4-24e99d014164",
            "active": false
        },
        {
            "id": "8570bd3d-50a4-4002-b313-6d2d3a115d0d",
            "name": "Quimm",
            "email": "ofreeman2q@engadget.com",
            "phoneNumber": "567-432-7082",
            "code": "11111111",
            "addressFact": "PO Box 95220",
            "syncId": "8c0fcbfa-0586-43c5-af12-f67f5aa8fb72",
            "active": true
        },
        {
            "id": "0f57196d-37a4-4dbd-9311-49e907b8afe5",
            "name": "Lazz",
            "email": "fsimonot2r@nytimes.com",
            "phoneNumber": "869-122-0256",
            "code": "11111111",
            "addressFact": "Apt 282",
            "syncId": "16dbe0de-4044-4b20-a0f3-33f5c9ee0dd3",
            "active": true
        }
    ],
    "clientrelatedentity": [
        {
            "id": "c392e807-f806-4e7c-b758-e1411607b23e",
            "code": "Lazz Client 1",
            "client": {
                "id": "0f57196d-37a4-4dbd-9311-49e907b8afe5",
                "code": "Lazz"
            },
            "syncId": "9bf157f1-e56e-4d49-9985-12290450fd74",
            "inn": "293123",
            "kpp": "12341234",
            "isShipper": true,
            "isConsignee": false,
            "isCarrier": false,
            "active": true
        },
        {
            "id": "c312e807-f806-4e7c-b758-e1411607b23e",
            "code": "Lazz Client 2",
            "client": {
                "id": "0f57196d-37a4-4dbd-9311-49e907b8afe5",
                "code": "Lazz"
            },
            "syncId": "9b1157f1-e56e-4d49-9985-12290450fd74",
            "inn": "29332123",
            "kpp": "1234123234",
            "isShipper": true,
            "isConsignee": false,
            "isCarrier": false,
            "active": true
        }
    ],
    "contract": [
        {
            "id": "4a1a9e44-96e5-4c23-86ab-a4d1fbaf75e5",
            "code": "Meemm",
            "company": "Meetz",
            "contractNumber": "691-83-9075",
            "validFrom": "2021-06-18T18:13:35Z",
            "validTo": "2023-08-24T17:36:28Z",
            "active": true,
            "currency": "MYR",
            "contractDate": "2020-11-28T02:23:14Z"
        },
        {
            "id": "8062e31a-0efb-45a0-92ac-960ba38c1f61",
            "code": "Npath",
            "company": "Livefish",
            "contractNumber": "131-94-2828",
            "validFrom": "2021-10-06T00:14:17Z",
            "validTo": "2024-01-31T08:51:16Z",
            "active": true,
            "currency": "ARS",
            "contractDate": "2020-12-30T07:26:49Z"
        },
        {
            "id": "0c6f544f-6b26-40d1-8859-a20689bb10dd",
            "code": "Vidoo",
            "company": "Quamba",
            "contractNumber": "211-16-8538",
            "validFrom": "2021-09-19T00:36:03Z",
            "validTo": "2023-09-13T00:13:09Z",
            "active": false,
            "currency": "CNY",
            "contractDate": "2020-06-22T13:34:54Z"
        },
        {
            "id": "96fd582f-7e76-49e1-9234-9a98b5218e7a",
            "code": "Realblab",
            "company": "Avamm",
            "contractNumber": "847-95-3197",
            "validFrom": "2021-07-02T09:20:50Z",
            "validTo": "2024-05-21T09:28:10Z",
            "active": false,
            "currency": "USD",
            "contractDate": "2020-10-08T05:19:38Z"
        },
        {
            "id": "edef317b-203e-4076-a5d7-60de0b3e5d16",
            "code": "Roodel",
            "company": "Brainsphere",
            "contractNumber": "858-29-8286",
            "validFrom": "2023-02-06T11:51:46Z",
            "validTo": "2023-12-08T16:06:03Z",
            "active": false,
            "currency": "RUB",
            "contractDate": "2020-12-14T19:15:55Z"
        },
        {
            "id": "260b4236-23b5-4beb-8788-ff609c41d110",
            "code": "Dynazzy",
            "company": "Jamia",
            "contractNumber": "475-25-5471",
            "validFrom": "2022-06-26T01:18:33Z",
            "validTo": "2024-01-02T01:19:24Z",
            "active": false,
            "currency": "TZS",
            "contractDate": "2021-01-01T21:49:32Z"
        },
        {
            "id": "462e0fa5-0a12-466a-9232-c449843c466b",
            "code": "Kanoodle",
            "company": "Flashdog",
            "contractNumber": "702-45-6560",
            "validFrom": "2022-04-04T03:57:03Z",
            "validTo": "2023-09-08T08:51:55Z",
            "active": true,
            "currency": "MNT",
            "contractDate": "2021-02-24T14:52:55Z"
        },
        {
            "id": "fd844eb7-5739-41bc-b166-04ad35e7e3e7",
            "code": "Trunyx",
            "company": "Flipopia",
            "contractNumber": "317-61-4998",
            "validFrom": "2023-02-03T03:13:56Z",
            "validTo": "2023-12-15T02:45:44Z",
            "active": true,
            "currency": "EGP",
            "contractDate": "2021-05-03T20:21:16Z"
        },
        {
            "id": "7a481ad2-ec63-441d-b447-bac75989bcab",
            "code": "Oyondu",
            "company": "Zoomlounge",
            "contractNumber": "813-10-5359",
            "validFrom": "2022-09-17T13:18:30Z",
            "validTo": "2023-12-03T21:32:27Z",
            "active": true,
            "currency": "CNY",
            "contractDate": "2020-06-30T07:12:45Z"
        },
        {
            "id": "657a36e5-64ef-40ba-b83f-ad347b158c9f",
            "code": "Devshare",
            "company": "Zoomzone",
            "contractNumber": "223-22-9365",
            "validFrom": "2021-08-14T20:58:51Z",
            "validTo": "2024-05-14T00:32:57Z",
            "active": true,
            "currency": "CNY",
            "contractDate": "2020-10-01T10:55:19Z"
        },
        {
            "id": "7ea0ff09-b794-42f2-b349-d811477a7603",
            "code": "Realbuzz",
            "company": "Zoonder",
            "contractNumber": "859-63-9423",
            "validFrom": "2023-01-14T10:27:05Z",
            "validTo": "2023-12-21T23:47:38Z",
            "active": true,
            "currency": "CZK",
            "contractDate": "2021-01-31T23:51:16Z"
        },
        {
            "id": "6492ce25-7d59-464a-b1eb-a5896cb2e80f",
            "code": "Brainverse",
            "company": "Jaxbean",
            "contractNumber": "228-60-4756",
            "validFrom": "2023-03-26T01:16:21Z",
            "validTo": "2023-11-25T13:40:05Z",
            "active": true,
            "currency": "MGA",
            "contractDate": "2020-09-25T15:24:17Z"
        },
        {
            "id": "e26fc53f-ceed-4921-b29a-be04877f725a",
            "code": "Photolist",
            "company": "Edgeify",
            "contractNumber": "811-56-9000",
            "validFrom": "2023-05-11T00:10:38Z",
            "validTo": "2024-01-06T09:27:55Z",
            "active": true,
            "currency": "USD",
            "contractDate": "2020-08-20T05:21:45Z"
        },
        {
            "id": "85a52848-da0f-4a05-8bff-fd18298f3f70",
            "code": "Browsecat",
            "company": "Shufflebeat",
            "contractNumber": "435-64-0406",
            "validFrom": "2022-09-30T00:02:44Z",
            "validTo": "2024-04-16T11:58:46Z",
            "active": true,
            "currency": "MYR",
            "contractDate": "2021-05-04T18:43:27Z"
        },
        {
            "id": "82a6d60a-fe34-42ac-954a-8b5bb78dcd31",
            "code": "Agimba",
            "company": "Devpulse",
            "contractNumber": "761-97-5414",
            "validFrom": "2022-09-26T04:02:20Z",
            "validTo": "2023-11-21T15:54:49Z",
            "active": false,
            "currency": "IDR",
            "contractDate": "2020-08-09T01:40:34Z"
        },
        {
            "id": "e16e6b7f-575c-4d3c-9790-5dc2be6460ef",
            "code": "Izio",
            "company": "Youopia",
            "contractNumber": "229-94-0212",
            "validFrom": "2022-09-05T00:49:24Z",
            "validTo": "2024-04-09T19:44:25Z",
            "active": true,
            "currency": "PEN",
            "contractDate": "2020-10-30T13:43:10Z"
        },
        {
            "id": "b6c245c9-6578-4f1b-b732-e730ee300390",
            "code": "Babbleset",
            "company": "Cogilith",
            "contractNumber": "863-04-2575",
            "validFrom": "2022-11-02T01:10:14Z",
            "validTo": "2023-11-02T06:39:12Z",
            "active": true,
            "currency": "PEN",
            "contractDate": "2020-08-26T15:42:04Z"
        },
        {
            "id": "864550db-a7b3-4895-94fc-a85ad8a9a6c8",
            "code": "Linkbridge",
            "company": "Mita",
            "contractNumber": "800-41-1742",
            "validFrom": "2023-04-04T09:24:19Z",
            "validTo": "2024-03-07T04:42:38Z",
            "active": false,
            "currency": "PLN",
            "contractDate": "2021-02-25T09:47:15Z"
        },
        {
            "id": "79859ee9-e479-4a1a-8ded-3d6ee1945ef5",
            "code": "Blogpad",
            "company": "Youspan",
            "contractNumber": "266-61-8226",
            "validFrom": "2021-09-28T17:26:39Z",
            "validTo": "2023-12-23T03:37:04Z",
            "active": false,
            "currency": "RUB",
            "contractDate": "2020-11-02T00:24:00Z"
        },
        {
            "id": "3353e178-4b88-453b-a7ea-c7ac2dc186c2",
            "code": "Devify",
            "company": "Zooveo",
            "contractNumber": "680-97-7222",
            "validFrom": "2022-09-10T15:08:45Z",
            "validTo": "2023-08-30T00:34:06Z",
            "active": false,
            "currency": "CZK",
            "contractDate": "2020-11-11T10:16:31Z"
        }
    ],
    "service": [
        {
            "id": "5d908e5f-64c4-4fcf-9584-ea31c45bfd2c",
            "code": "Механизированный прием товара",
            "terminalArea": {
                "id": "123-123",
                "code": "Складской комплекс"
            },
            "unitOfMeasure": {
                "id": "123-222",
                "code": "пл."
            },
            "accrualMethod": {
                "id": "1",
                "code": "Операции"
            },
            "accrualBase": {
                "id": "2",
                "code": "Количество"
            },
            "active": true,
            "instruction": "1. Сверить пломбы в соответствии с документацией;  2. Выгрузить монопаллеты из кузова ТС;  3. Оформить акты М-7 4. Идентифицировать монопаллеты",
            "name": "Сверка пломб в соответствии с документацией; выгрузка монопаллеты из кузова ТС; оформление акта М-7, идентификация монопаллеты; проверка на видимые внешние повреждения монопаллеты и поддона; перемещение монопаллеты из зоны приемки в зону хранения; внесение информации о приёмке Товара в складскую систему учёта Хранителя."
        }
    ],
    "remainscontainers": [
        {
            "id": "1",
            "code": "OOLU9013240",
            "transport": "ЖД",
            "transportCode": "59520890",
            "good": {
                "id": "12",
                "code": "Полиэтилен"
            },
            "date": "06.10.2024 10:50",
            "order": "361",
            "orderStatus": "Выполнена",
            "client": "АО «Смартлог»"
        },
        {
            "id": "2",
            "code": "DLRU0009607",
            "transport": "ЖД",
            "transportCode": "98113590",
            "good": {
                "id": "13",
                "code": "Полипропилен"
            },
            "date": "01.10.2024 17:30",
            "order": "453",
            "orderStatus": "Выполнена",
            "client": "ПАО «СИБУРХОЛДИНГ»"
        }
    ]
}
